Metadata-Version: 2.1
Name: bmstu-schedule
Version: 1.5.1
Summary: BMSTU EU Schedule iCal parser
Home-page: https://github.com/BMSTU-Schedule/bmstu-schedule-parser
Author: George Gabolaev
Author-email: gabolaev98@gmail.com
License: AGPLv3
Platform: UNKNOWN
Requires-Python: >=3.5
